cpagym/__init__.py
cpagym/agent/__init__.py
cpagym/agent/ddpg_agent.py
cpagym/agent/dqn_agent.py
cpagym/algorithm/111.py
cpagym/algorithm/222.py
cpagym/algorithm/Actor_Critic.py
cpagym/algorithm/DQN.py
cpagym/algorithm/__init__.py
cpagym/component/__init__.py
cpagym/component/ounoise.py
cpagym/component/replaybuffer.py
cpagym/envs/__init__.py
cpagym/envs/financial_market_env.py
cpagym/envs/moral_hazard_env.py
cpagym/envs/new.py
cpagym/train/__init__.py
cpagym/train/dqn_train.py
cpagym/wrappers/__init__.py
cpagym/wrappers/clip_reward.py
cpagym/wrappers/discrete_actions.py
cpagym/wrappers/reacher_weighted_reward.py
cpagym/wrappers/relative_position.py
cpagym-0.1.17.dist-info/LICENSE
cpagym-0.1.17.dist-info/METADATA
cpagym-0.1.17.dist-info/WHEEL
cpagym-0.1.17.dist-info/top_level.txt
cpagym-0.1.17.dist-info/RECORD
