Metadata-Version: 2.1
Name: cpagym
Version: 0.1.17
Summary: Accounting  Reinforcement Learning GYM for Ai-Accountants .为会计人打造的专属智能会计强化学习框架。
Home-page: https://cpanlp.com
Author: Draco Deng
Author-email: dracodeng6@gmail.com
Keywords: python, Reinforcement Learning,gym,openaiaccounting,cpa,audit,intelligent accounting,linguistic turn,linguistic,intelligent audit,natural language processing,machine learning,finance,certified public accountant,big four,会计,强化学习,注会,注册会计师,审计,智能会计,会计的语言学转向,语言学,智能审计,自然语言处理,机器学习,金融,北外,财会,四大,会计智能体
Classifier: Development Status :: 5 - Production/Stable
Classifier: Intended Audience :: Developers
Classifier: Intended Audience :: Financial and Insurance Industry
Classifier: Programming Language :: Python :: 3
Classifier: Operating System :: Unix
Classifier: Operating System :: MacOS :: MacOS X
Classifier: Operating System :: Microsoft :: Windows
License-File: LICENSE
